Metadata-Version: 2.1
Name: ksconf
Version: 0.13.10
Summary: KSCONF: Ksconf Splunk Configuration Tool
Home-page: https://github.com/Kintyre/ksconf
Author: Lowell Alleman
Author-email: lowell@kintyre.co
License: Apache Software License
Project-URL: Documentation, https://ksconf.readthedocs.io/
Project-URL: Splunk app, https://splunkbase.splunk.com/app/4383/
Keywords: ksconf splunk kinytre conf tool
Classifier: Development Status :: 4 - Beta
Classifier: Environment :: Console
Classifier: Intended Audience :: System Administrators
Classifier: License :: OSI Approved :: Apache Software License
Classifier: Natural Language :: English
Classifier: Operating System :: MacOS :: MacOS X
Classifier: Operating System :: Microsoft :: Windows
Classifier: Operating System :: POSIX :: Linux
Classifier: Programming Language :: Python :: 3
Classifier: Programming Language :: Python :: 3.7
Classifier: Programming Language :: Python :: 3.8
Classifier: Programming Language :: Python :: 3.9
Classifier: Programming Language :: Python :: 3.10
Classifier: Programming Language :: Python :: 3.11
Classifier: Topic :: Utilities
Requires-Python: >=3.7
License-File: LICENSE
Requires-Dist: splunk-sdk>=1.7.0
Requires-Dist: pluggy>=1.2.0
Requires-Dist: importlib-metadata>4.6; python_version < "3.10"
Provides-Extra: bash
Requires-Dist: argcomplete; extra == "bash"
Provides-Extra: fully-loaded
Requires-Dist: lxml; extra == "fully-loaded"
Requires-Dist: argcomplete; extra == "fully-loaded"
Requires-Dist: jinja2; extra == "fully-loaded"
Requires-Dist: splunk-sdk; extra == "fully-loaded"
Requires-Dist: pyyaml; extra == "fully-loaded"
Provides-Extra: jinja
Requires-Dist: jinja2; extra == "jinja"
Provides-Extra: thirdparty
Requires-Dist: splunk-sdk>=1.7.0; extra == "thirdparty"
Requires-Dist: lxml; extra == "thirdparty"
Provides-Extra: xml
Requires-Dist: lxml; extra == "xml"
